{
  "name": "Dragon Egg - The Legacy of the Red Dragon",
  "description": "The dragon egg are the legacy of the Red Dragon. The owner of the egg play important part in the Red Dragon Ghost Guild, be sure to !PROTECT 🛡️ the Dragon Egg at all costs.",
  "image": "https://raw.githubusercontent.com/Dragon Egg/DragonEggNFT/image/unrevealed.png",
  "cover_image": "https://raw.githubusercontent.com/johnnylcy/RedDragonGhost/main/DragonEggNFT/image/example/example.png",
  "social_links": [
    "https://t.me/RedDragonGhost",
    "https://t.me/RDGGuild",
    "https://t.me/DragonEggStory"
  ]
}

